shipyard_bp_utils/__init__.py
shipyard_bp_utils/args.py
shipyard_bp_utils/artifacts.py
shipyard_bp_utils/files.py
shipyard_bp_utils/text.py
shipyard_bp_utils-1.3.3.dist-info/METADATA
shipyard_bp_utils-1.3.3.dist-info/WHEEL
shipyard_bp_utils-1.3.3.dist-info/top_level.txt
shipyard_bp_utils-1.3.3.dist-info/RECORD
