Metadata-Version: 2.4
Name: shipyard-bp-utils
Version: 1.3.3
Summary: Utility functions for blueprints
Requires-Python: >=3.11
Requires-Dist: python-dateutil>=2.8.2
Requires-Dist: shipyard-templates>=0.9.0
